datashop/__init__.py
datashop/datashop.py
datashop-0.0.3.dist-info/LICENSE
datashop-0.0.3.dist-info/METADATA
datashop-0.0.3.dist-info/WHEEL
datashop-0.0.3.dist-info/top_level.txt
datashop-0.0.3.dist-info/RECORD
